{"State.c6b66951-952e-47ba-999c-5cb64b750da6": {"id": "c6b66951-952e-47ba-999c-5cb64b750da6", "created_at": "2023-11-21T20:58:57.457736", "updated_at": "2023-11-21T20:58:57.457739", "name": "California", "__class__": "State"}, "State.8cc84dce-a44d-44bf-8898-31049e52874f": {"id": "8cc84dce-a44d-44bf-8898-31049e52874f", "created_at": "2023-11-21T20:58:57.458070", "updated_at": "2023-11-21T20:58:57.458073", "name": "Arizona", "__class__": "State"}, "Place.1cefe085-57e4-41f2-b812-c4e1935e94b3": {"id": "1cefe085-57e4-41f2-b812-c4e1935e94b3", "created_at": "2023-11-21T20:58:57.459967", "updated_at": "2023-11-21T20:58:57.459969", "city_id": "0001", "user_id": "0001", "name": "My_little_house", "number_rooms": 4, "number_bathrooms": 2, "max_guest": 10, "price_by_night": 300, "latitude": 37.773972, "longitude": -122.431297, "__class__": "Place"}, "State.7d0e2c6f-6789-47ed-a586-75e522d41b7c": {"id": "7d0e2c6f-6789-47ed-a586-75e522d41b7c", "created_at": "2023-11-21T21:05:19.356003", "updated_at": "2023-11-21T21:05:19.356006", "name": "California", "__class__": "State"}, "State.4ca9251a-e369-4bb9-9bb7-baf3450a23c9": {"id": "4ca9251a-e369-4bb9-9bb7-baf3450a23c9", "created_at": "2023-11-21T21:05:19.357284", "updated_at": "2023-11-21T21:05:19.357287", "name": "Arizona", "__class__": "State"}, "Place.2d62e2e1-51f5-4019-87be-6cf5950653df": {"id": "2d62e2e1-51f5-4019-87be-6cf5950653df", "created_at": "2023-11-21T21:05:19.359195", "updated_at": "2023-11-21T21:05:19.359198", "city_id": "0001", "user_id": "0001", "name": "My_little_house", "number_rooms": 4, "number_bathrooms": 2, "max_guest": 10, "price_by_night": 300, "latitude": 37.773972, "longitude": -122.431297, "__class__": "Place"}}